djangocms_frontend/__init__.py
djangocms_frontend/apps.py
djangocms_frontend/cms_plugins.py
djangocms_frontend/component_base.py
djangocms_frontend/component_pool.py
djangocms_frontend/fields.py
djangocms_frontend/helpers.py
djangocms_frontend/models.py
djangocms_frontend/plugin_tag.py
djangocms_frontend/settings.py
djangocms_frontend/ui_plugin_base.py
djangocms_frontend/views.py
djangocms_frontend/common/__init__.py
djangocms_frontend/common/attributes.py
djangocms_frontend/common/title.py
djangocms_frontend/common/bootstrap5/__init__.py
djangocms_frontend/common/bootstrap5/background.py
djangocms_frontend/common/bootstrap5/responsive.py
djangocms_frontend/common/bootstrap5/sizing.py
djangocms_frontend/common/bootstrap5/spacing.py
djangocms_frontend/common/tailwind/spacing.py
djangocms_frontend/contrib/__init__.py
djangocms_frontend/contrib/accordion/__init__.py
djangocms_frontend/contrib/accordion/cms_plugins.py
djangocms_frontend/contrib/accordion/forms.py
djangocms_frontend/contrib/accordion/models.py
djangocms_frontend/contrib/accordion/frameworks/__init__.py
djangocms_frontend/contrib/accordion/frameworks/bootstrap5.py
djangocms_frontend/contrib/accordion/migrations/0001_initial.py
djangocms_frontend/contrib/accordion/migrations/__init__.py
djangocms_frontend/contrib/accordion/templates/djangocms_frontend/bootstrap5/accordion.html
djangocms_frontend/contrib/accordion/templates/djangocms_frontend/bootstrap5/accordion_item.html
djangocms_frontend/contrib/alert/__init__.py
djangocms_frontend/contrib/alert/cms_plugins.py
djangocms_frontend/contrib/alert/forms.py
djangocms_frontend/contrib/alert/models.py
djangocms_frontend/contrib/alert/frameworks/__init__.py
djangocms_frontend/contrib/alert/frameworks/bootstrap5.py
djangocms_frontend/contrib/alert/frameworks/foundation6.py
djangocms_frontend/contrib/alert/migrations/0001_initial.py
djangocms_frontend/contrib/alert/migrations/__init__.py
djangocms_frontend-2.3.0.dist-info/licenses/LICENSE
djangocms_frontend-2.3.0.dist-info/METADATA
djangocms_frontend-2.3.0.dist-info/WHEEL
djangocms_frontend-2.3.0.dist-info/top_level.txt
djangocms_frontend-2.3.0.dist-info/RECORD
