Metadata-Version: 2.4
Name: djangocms-frontend
Version: 2.3.0
Summary: Adds abstract User Interface items as plugins to django CMS.
Author-email: Fabian Braun <fsbraun@gmx.de>
License-Expression: BSD-3-Clause
Project-URL: Documentation, https://djangocms-frontend.readthedocs.io
Project-URL: Issues, https://github.com/django-cms/djangocms-frontend/issues
Project-URL: Release notes, https://github.com/django-cms/djangocms-frontend/blob/master/CHANGELOG.rst
Project-URL: Source, https://github.com/django-cms/djangocms-frontend
Classifier: Development Status :: 5 - Production/Stable
Classifier: Framework :: Django
Classifier: Framework :: Django :: 4.2
Classifier: Framework :: Django :: 5.0
Classifier: Framework :: Django :: 5.1
Classifier: Framework :: Django :: 5.2
Classifier: Framework :: Django CMS
Classifier: Framework :: Django CMS :: 3.11
Classifier: Framework :: Django CMS :: 4.1
Classifier: Framework :: Django CMS :: 5.0
Classifier: Programming Language :: Python :: 3 :: Only
Classifier: Programming Language :: Python :: 3.10
Classifier: Programming Language :: Python :: 3.11
Classifier: Programming Language :: Python :: 3.12
Classifier: Programming Language :: Python :: 3.13
Classifier: Programming Language :: Python :: 3.14
Requires-Python: >=3.10
License-File: LICENSE
Requires-Dist: django-cms>=3.7
Requires-Dist: django-entangled>=0.6
Requires-Dist: django-filer>=1.7
Requires-Dist: djangocms-attributes-field>=4
Requires-Dist: djangocms-link>=5
Requires-Dist: easy-thumbnails
Provides-Extra: cms-3
Requires-Dist: django-cms<4; extra == "cms-3"
Requires-Dist: django-parler; extra == "cms-3"
Requires-Dist: djangocms-link>=5; extra == "cms-3"
Requires-Dist: djangocms-text; extra == "cms-3"
Provides-Extra: cms-4
Requires-Dist: django-cms>=4.1; extra == "cms-4"
Requires-Dist: django-parler; extra == "cms-4"
Requires-Dist: djangocms-alias>=2; extra == "cms-4"
Requires-Dist: djangocms-link>=5; extra == "cms-4"
Requires-Dist: djangocms-text; extra == "cms-4"
Requires-Dist: djangocms-versioning>=2; extra == "cms-4"
Provides-Extra: djangocms-icon
Requires-Dist: djangocms-icon>=1.4; extra == "djangocms-icon"
Provides-Extra: static-ace
Requires-Dist: djangocms-static-ace; extra == "static-ace"
Dynamic: license-file
